{
    "1": {
        "lat": 38.0689193,
        "lng": -122.2303477
    },
    "2": {
        "lat": 37.3011274,
        "lng": -121.7650792
    },
    "3": {
        "lat": 34.0872692,
        "lng": -118.2924734
    },
    "4": {
        "lat": 37.9557822,
        "lng": -122.5496479
    },
    "5": {
        "lat": 37.535479,
        "lng": -122.3355121
    },
    "6": {
        "lat": 36.325102,
        "lng": -119.3149754
    },
    "7": {
        "lat": 32.8800604,
        "lng": -117.2340135
    },
    "8": {
        "lat": 39.6485275,
        "lng": -121.6449417
    },
    "9": {
        "lat": 35.5674569,
        "lng": -117.667777
    },
    "10": {
        "lat": 38.0317977,
        "lng": -120.3885135
    },
    "11": {
        "lat": 35.3050053,
        "lng": -120.6624942
    },
    "12": {
        "lat": 36.653712,
        "lng": -121.7989787
    },
    "13": {
        "lat": 37.789553,
        "lng": -122.165612
    },
    "14": {
        "lat": 33.7673604,
        "lng": -117.8681925
    },
    "16": {
        "lat": 35.32924990000001,
        "lng": -120.7400729
    },
    "17": {
        "lat": 37.3336715,
        "lng": -120.4729896
    },
    "18": {
        "lat": 36.778261,
        "lng": -119.4179324
    },
    "19": {
        "lat": 34.4747209,
        "lng": -117.2615981
    },
    "20": {
        "lat": 34.87031810000001,
        "lng": -117.0233643
    },
    "21": {
        "lat": 37.6560295,
        "lng": -122.0561984
    },
    "23": {
        "lat": 33.1298249,
        "lng": -117.1586856
    },
    "24": {
        "lat": 37.525398,
        "lng": -120.8554591
    },
    "25": {
        "lat": 34.0311432,
        "lng": -118.2702767
    },
    "26": {
        "lat": 32.7774047,
        "lng": -117.0714068
    },
    "27": {
        "lat": 38.6511479,
        "lng": -121.3467327
    },
    "28": {
        "lat": 37.9688909,
        "lng": -122.3400902
    },
    "29": {
        "lat": 36.8136777,
        "lng": -119.7461767
    },
    "30": {
        "lat": 33.7324231,
        "lng": -116.3872567
    },
    "31": {
        "lat": 33.7841338,
        "lng": -118.2840218
    },
    "32": {
        "lat": 37.3925485,
        "lng": -121.9828037
    },
    "33": {
        "lat": 37.72569,
        "lng": -122.4510797
    },
    "34": {
        "lat": 33.8774579,
        "lng": -118.2110328
    },
    "35": {
        "lat": 36.7669209,
        "lng": -119.7979063
    },
    "36": {
        "lat": 36.733611,
        "lng": -119.496389
    },
    "38": {
        "lat": 40.6255781,
        "lng": -122.3180956
    },
    "39": {
        "lat": 37.33874,
        "lng": -121.8852525
    },
    "40": {
        "lat": 38.9266515,
        "lng": -119.9725759
    },
    "41": {
        "lat": 36.9876108,
        "lng": -121.9259014
    },
    "42": {
        "lat": 34.2406756,
        "lng": -118.5300196
    },
    "43": {
        "lat": 34.16636,
        "lng": -118.2281216
    },
    "44": {
        "lat": 34.1753399,
        "lng": -118.4189817
    },
    "45": {
        "lat": 32.9072307,
        "lng": -117.1193489
    },
    "46": {
        "lat": 33.9737055,
        "lng": -117.3280644
    },
    "47": {
        "lat": 34.3151336,
        "lng": -118.4192444
    },
    "48": {
        "lat": 37.5293321,
        "lng": -121.9145556
    },
    "49": {
        "lat": 34.1439461,
        "lng": -118.118761
    },
    "50": {
        "lat": 33.8624581,
        "lng": -118.2544108
    },
    "51": {
        "lat": 37.3614878,
        "lng": -122.1283277
    },
    "52": {
        "lat": 37.6392595,
        "lng": -120.9970014
    },
    "53": {
        "lat": 33.80662210000001,
        "lng": -116.9694101
    },
    "54": {
        "lat": 32.7175697,
        "lng": -117.1508543
    },
    "55": {
        "lat": 33.7339347,
        "lng": -118.0033108
    },
    "56": {
        "lat": 33.1512505,
        "lng": -117.1821885
    },
    "57": {
        "lat": 38.45573,
        "lng": -122.7211551
    },
    "58": {
        "lat": 37.8699811,
        "lng": -122.2698694
    },
    "60": {
        "lat": 38.578467,
        "lng": -121.4953083
    },
    "61": {
        "lat": 38.0057947,
        "lng": -121.8608721
    },
    "62": {
        "lat": 34.0487487,
        "lng": -117.8421321
    },
    "63": {
        "lat": 33.6610426,
        "lng": -114.6529049
    },
    "64": {
        "lat": 34.0190058,
        "lng": -118.0347181
    },
    "65": {
        "lat": 33.5542768,
        "lng": -117.6640079
    },
    "66": {
        "lat": 37.3541079,
        "lng": -121.9552356
    },
    "67": {
        "lat": 36.1533088,
        "lng": -120.3512954
    },
    "68": {
        "lat": 37.4473859,
        "lng": -122.2652419
    },
    "69": {
        "lat": 34.1467226,
        "lng": -117.5708601
    },
    "70": {
        "lat": 34.0391513,
        "lng": -117.1012275
    },
    "71": {
        "lat": 33.8278801,
        "lng": -118.0237357
    },
    "72": {
        "lat": 36.9732557,
        "lng": -121.5685598
    },
    "73": {
        "lat": 38.2742517,
        "lng": -122.2760808
    },
    "74": {
        "lat": 33.6707019,
        "lng": -117.9092172
    },
    "75": {
        "lat": 34.0555994,
        "lng": -117.819263
    },
    "76": {
        "lat": 34.0663797,
        "lng": -118.1684782
    },
    "77": {
        "lat": 37.7971301,
        "lng": -122.2634909
    },
    "78": {
        "lat": 33.9711925,
        "lng": -117.3811035
    },
    "79": {
        "lat": 37.87015100000001,
        "lng": -122.2594606
    },
    "80": {
        "lat": 37.263434,
        "lng": -122.0100493
    },
    "81": {
        "lat": 33.7838235,
        "lng": -118.1140904
    },
    "82": {
        "lat": 40.4315267,
        "lng": -120.6325811
    },
    "83": {
        "lat": 40.698432,
        "lng": -124.1953753
    },
    "84": {
        "lat": 35.4083127,
        "lng": -118.9716398
    },
    "85": {
        "lat": 34.1813584,
        "lng": -117.3231875
    },
    "86": {
        "lat": 34.183637,
        "lng": -118.5801887
    },
    "87": {
        "lat": 34.1648731,
        "lng": -119.1557205
    },
    "88": {
        "lat": 38.291859,
        "lng": -122.4580356
    },
    "89": {
        "lat": 38.5382322,
        "lng": -121.7617125
    },
    "90": {
        "lat": 39.1272977,
        "lng": -121.539451
    },
    "91": {
        "lat": 34.0040139,
        "lng": -118.3868556
    },
    "92": {
        "lat": 34.4051462,
        "lng": -119.6992036
    },
    "93": {
        "lat": 38.7909585,
        "lng": -121.2108548
    },
    "94": {
        "lat": 38.2352198,
        "lng": -122.119899
    },
    "95": {
        "lat": 34.2761617,
        "lng": -119.2299773
    },
    "96": {
        "lat": 37.6427231,
        "lng": -122.1062344
    },
    "97": {
        "lat": 34.1333259,
        "lng": -117.8851136
    },
    "98": {
        "lat": 35.3486641,
        "lng": -119.1033448
    },
    "99": {
        "lat": 32.7446539,
        "lng": -116.9404423
    },
    "100": {
        "lat": 39.1895625,
        "lng": -123.2277897
    },
    "101": {
        "lat": 32.8049085,
        "lng": -117.1675503
    },
    "102": {
        "lat": 41.4129975,
        "lng": -122.3890908
    },
    "103": {
        "lat": 33.8842409,
        "lng": -118.3302549
    },
    "104": {
        "lat": 33.886564,
        "lng": -118.0991837
    },
    "105": {
        "lat": 36.778261,
        "lng": -119.4179324
    },
    "106": {
        "lat": 32.8166735,
        "lng": -117.0065725
    },
    "107": {
        "lat": 32.8283376,
        "lng": -115.5035534
    },
    "108": {
        "lat": 33.1927582,
        "lng": -117.3093114
    },
    "109": {
        "lat": 37.9953671,
        "lng": -121.3195528
    },
    "110": {
        "lat": 34.9446133,
        "lng": -120.4189337
    },
    "111": {
        "lat": 37.7823036,
        "lng": -122.2793551
    },
    "112": {
        "lat": 34.1410598,
        "lng": -116.2169342
    },
    "113": {
        "lat": 37.3192806,
        "lng": -122.0447919
    },
    "114": {
        "lat": 37.9686774,
        "lng": -122.0711537
    },
    "115": {
        "lat": 40.8747332,
        "lng": -124.0789268
    },
    "116": {
        "lat": 37.7241492,
        "lng": -122.4799405
    },
    "117": {
        "lat": 34.0699182,
        "lng": -118.4438495
    },
    "118": {
        "lat": 34.0414348,
        "lng": -118.1501982
    },
    "119": {
        "lat": 35.1492183,
        "lng": -119.4601285
    },
    "120": {
        "lat": 33.6423814,
        "lng": -117.8416747
    },
    "121": {
        "lat": 34.6777643,
        "lng": -118.1876041
    },
    "122": {
        "lat": 39.9502368,
        "lng": -120.9692806
    },
    "123": {
        "lat": 36.6741645,
        "lng": -121.6676283
    },
    "124": {
        "lat": 33.6757551,
        "lng": -117.7793915
    },
    "125": {
        "lat": 36.0491632,
        "lng": -119.0143883
    },
    "126": {
        "lat": 37.3541079,
        "lng": -121.9552356
    },
    "127": {
        "lat": 37.6300657,
        "lng": -122.4659034
    },
    "128": {
        "lat": 34.4139629,
        "lng": -119.848947
    },
    "129": {
        "lat": 33.8823476,
        "lng": -117.8851033
    },
    "130": {
        "lat": 33.9292982,
        "lng": -118.3055411
    },
    "131": {
        "lat": 34.086308,
        "lng": -117.3076518
    },
    "132": {
        "lat": 36.9905322,
        "lng": -122.0584354
    },
    "133": {
        "lat": 36.5893339,
        "lng": -121.8869455
    },
    "134": {
        "lat": 33.8758501,
        "lng": -117.9176642
    },
    "135": {
        "lat": 33.8335679,
        "lng": -118.1345668
    },
    "136": {
        "lat": 37.3146585,
        "lng": -121.9272308
    },
    "137": {
        "lat": 34.0167814,
        "lng": -118.4706934
    },
    "138": {
        "lat": 32.6400996,
        "lng": -116.9978233
    },
    "139": {
        "lat": 34.3015682,
        "lng": -118.8364075
    },
    "140": {
        "lat": 34.4042187,
        "lng": -118.5696313
    },
    "141": {
        "lat": 39.7296653,
        "lng": -121.8478871
    },
    "142": {
        "lat": 38.4541192,
        "lng": -121.4227382
    },
    "143": {
        "lat": 34.1620556,
        "lng": -119.043463
    },
    "144": {
        "lat": 37.3647026,
        "lng": -120.4240941
    },
    "145": {
        "lat": 38.6615323,
        "lng": -121.1271228
    },
    "146": {
        "lat": 36.2923509,
        "lng": -119.82301
    },
    "147": {
        "lat": 38.6605655,
        "lng": -121.7356304
    },
    "148": {
        "lat": 33.9174931,
        "lng": -117.5689082
    },
    "149": {
        "lat": 33.886786,
        "lng": -117.2029323
    },
    "150": {
        "lat": 36.887979,
        "lng": -119.732427
    },
    "153": {
        "lat": 33.8774579,
        "lng": -118.2110328
    },
    "200": {
        "lat": 36.778261,
        "lng": -119.4179324
    }
}